<mvc:View
    xmlns='sap.m'
    xmlns:uxap='sap.uxap'
    xmlns:form='sap.ui.layout.form'
    xmlns:core='sap.ui.core'
    xmlns:mvc='sap.ui.core.mvc'
	controllerName='planner.controller.todo.detailDetail.TodoDetailDetail'>

    <uxap:ObjectPageLayout
        upperCaseAnchorBar='false'
        useIconTabBar='true'>

        <!-- HEADER -->
        <uxap:headerTitle>
            <uxap:ObjectPageDynamicHeaderTitle>

                <uxap:breadcrumbs>
                    <Breadcrumbs currentLocationText='{todo>name}'>
                        <links>
                            <Link press='onPressCloseAllPages' text='Списки Дел' />
                            <Link press='onPressClosePage' text='{todo>list/name}' />
                        </links>
                    </Breadcrumbs>
                </uxap:breadcrumbs>

                <uxap:navigationActions>
                    <Button
                        press='onPressClosePage'
                        icon='sap-icon://decline' />
                </uxap:navigationActions>

                <uxap:actions>
                    <Button
                        press='onPressDelete'
                        text='Удалить'
                        icon='sap-icon://delete'
                        type='Reject'>
                        <layoutData>
                            <OverflowToolbarLayoutData priority='AlwaysOverflow' />
                        </layoutData>
                    </Button>
                </uxap:actions>

                <uxap:expandedHeading>
                    <Title text='{todo>name}' wrapping='true' />
                </uxap:expandedHeading>

                <uxap:expandedContent>
                    <ObjectStatus title='Обновлено' text='{todo>modifiedAt}' />
                </uxap:expandedContent>

                <uxap:snappedHeading>
                    <Title text='{todo>name}' wrapping='true' />
                </uxap:snappedHeading>

                <uxap:snappedContent>
                    <ObjectStatus title='Обновлено' text='{todo>modifiedAt}' />
                </uxap:snappedContent>

                <uxap:content>
                    <GenericTag
                        design='StatusIconHidden'
                        text='{ path: "todo>priority", formatter: ".Formatter.getPriorityText" }'
                        status='{ path: "todo>priority", formatter: ".Formatter.getPriorityState" }' />
                </uxap:content>

            </uxap:ObjectPageDynamicHeaderTitle>
        </uxap:headerTitle>

        <!-- HEADER CONTENT -->
        <uxap:headerContent>
            <form:SimpleForm
                editable='true'
                layout='ColumnLayout'
                columnsL='1'
                labelSpanL='12'
                columnsM='1'
                labelSpanM='12'>
                <form:content>
                    <core:Title text='Общее' />
                    <Label text='Название' />
                    <Input id='idTodoParentNameInput' value='{todo>name}' />

                    <Label text='Приоритет' />
                    <Select
                        forceSelection='false'
                        selectedKey='{todo>priority}'
                        items='{common>/PriorityCode}'>
                        <items>
                            <core:Item key='{common>code}' text='{common>name}' />
                        </items>
                    </Select>

                    <Label text='Заметки' />
                    <TextArea rows='5' value='{todo>info}' />

                </form:content>
            </form:SimpleForm>
        </uxap:headerContent>

        <!-- SECTIONS -->
        <uxap:sections>
            <!-- INFORMATION -->
            <uxap:ObjectPageSection title='Заметки' titleUppercase='false'>
                <uxap:subSections>
                    <uxap:ObjectPageSubSection>
                        <uxap:blocks>
                            <Text text='{todo>info}' emptyIndicatorMode='{= !!%{todo>info} ? "Off" : "On" }'/>
                        </uxap:blocks>
                    </uxap:ObjectPageSubSection>
                </uxap:subSections>
            </uxap:ObjectPageSection>
            
            <!-- ACTIVITIES -->
            <uxap:ObjectPageSection title='Шаги ({todo>items/$count})' titleUppercase='false'>
                <uxap:subSections>
                    <uxap:ObjectPageSubSection>
                        <uxap:blocks>
                            <Table
                                id='idTodoItemList'
                                delete='onPressDeleteTodoItem'
                                showSeparators='Inner'
                                sticky='ColumnHeaders,HeaderToolbar'
                                mode='{= %{config>/editTodoItems} ? "Delete" : "None"}'
                                items='{todo>items}'>

                                <noData>
                                    <IllustratedMessage illustrationType='sapIllus-NoActivities' />
                                </noData>

                                <headerToolbar>
                                    <OverflowToolbar>
                                        <Title text='Шаги ({todo>items/$count})' />
                                        <ToolbarSpacer />
                                        <ToggleButton
                                            icon='sap-icon://edit'
                                            tooltip='Редактировать'
                                            pressed='{config>/editTodoItems}'>
                                            <layoutData>
                                                <OverflowToolbarLayoutData priority='NeverOverflow' />
                                            </layoutData>
                                        </ToggleButton>
                                        <OverflowToolbarButton
                                            press='onPressAddTodoItem'
                                            icon='sap-icon://add'
                                            text='Добавить Шаг'
                                            tooltip='Добавить Шаг' />
                                    </OverflowToolbar>
                                </headerToolbar>

                                <columns>
                                    <Column>
                                        <Text text='Шаг' />
                                    </Column>
                                    <Column hAlign='Right'>
                                        <Text text='Приоритет' />
                                    </Column>
                                </columns>

                                <ColumnListItem>
                                    <cells>
                                        <VBox>
                                            <ObjectIdentifier
                                                title='{todo>name}'
                                                visible='{= !%{config>/editTodoItems} }'/>
                                            <Input
                                                value='{todo>name}'
                                                visible='{config>/editTodoItems}' />
                                            <ObjectStatus
                                                text='{path: "todo>status", formatter: ".Formatter.getProgressStatusText"}' 
                                                state='{path: "todo>status", formatter: ".Formatter.getProgressStatusState"}' />
                                        </VBox>
                                        <VBox>
                                            <GenericTag
                                                design='StatusIconHidden'
                                                text='{ path: "todo>priority", formatter: ".Formatter.getPriorityText" }'
                                                status='{ path: "todo>priority", formatter: ".Formatter.getPriorityState" }'
                                                visible='{= !%{config>/editTodoItems} }' />
                                            <Select
                                                selectedKey='{todo>priority}'
                                                visible='{config>/editTodoItems}'
                                                items='{path: "common>/PriorityCode", templateShareable: false}'>
                                                <items>
                                                    <core:Item key='{common>code}' text='{common>name}' />
                                                </items>
                                            </Select>
                                        </VBox>
                                    </cells>
                                </ColumnListItem>

                            </Table>
                        </uxap:blocks>
                    </uxap:ObjectPageSubSection>
                </uxap:subSections>
            </uxap:ObjectPageSection>
        </uxap:sections>

    </uxap:ObjectPageLayout>

</mvc:View>